asv_spyglass-0.1.0.dist-info/METADATA
asv_spyglass-0.1.0.dist-info/WHEEL
asv_spyglass-0.1.0.dist-info/entry_points.txt
asv_spyglass-0.1.0.dist-info/licenses/LICENSE.md
asv_spyglass/__init__.py
asv_spyglass/_asv_ro.py
asv_spyglass/_aux.py
asv_spyglass/cli.py
asv_spyglass/compare.py
asv_spyglass/results.py
asv_spyglass-0.1.0.dist-info/RECORD
