Metadata-Version: 2.1
Name: asv_spyglass
Version: 0.1.0
Summary: File oriented ASV benchmark comparer
Author-Email: Rohit Goswami <rgoswami@ieee.org>
License: MIT
Classifier: Programming Language :: Python :: 3
Classifier: Programming Language :: Python :: 3.12
Classifier: License :: OSI Approved :: MIT License
Classifier: Operating System :: OS Independent
Classifier: Topic :: System :: Benchmark
Requires-Python: >=3.12
Requires-Dist: asv>=0.6.5
Requires-Dist: click>=8.1.8
Requires-Dist: asv-runner>=0.2.1
Requires-Dist: polars>=1.20.0
Provides-Extra: test
Requires-Dist: pytest>=8.3.4; extra == "test"
Requires-Dist: approvaltests>=14.3.0; extra == "test"
Requires-Dist: pytest-datadir>=1.5.0; extra == "test"
